{"திரைப்படம்": "தியா", "பாடலாசிரியர்": "மதன் கார்க்கி", "இசையமைப்பாளர்": "சாம். சீ. எஸ்", "பாடல்": "கொஞ்சலி கொஞ்சலி", "வருடம்": "2018", "பாடியவர்கள்": "சத்யபிரகாஷ் டீ, நேகா வேனுகோபால், ஜே கே ஏ சாளினி", "பாடல்வரிகள்": "அழகுத்தி செஞ்சு வச்ச ஆலங்கட்டி ஆட்டம் கண்ணு அதனை பாத பொண்ணு  வா புள்ள என் கை கோத்து நீ இனி என் மூச்சு காத்து உமக்கு காத்து கேடந்தவ மனங்கு காத்த இப்ப  கொஞ்சலி கொஞ்சலி ராவெல்லாம் நீ என் ஜோலி  கொஞ்சலி கொஞ்சலி மஞ்சத்தில் நான் உன் ஜோலி  நான் தீண்டும் கனவு நீ  அழகுத்தி செஞ்சு வச்ச ஆலங்கட்டி ஆட்டம் கண்ணு அதனை தீத தின்னு  தூரிகை அதன் தூறலாய் உந்தன் காதலோ வீழ்கிறதே மாறினேன் நிறம் மாறினேன் எந்தன் நாணமோ நீள்கிறதே   காட்டில் வண்ணம் கூட்டும் மலரே என் விண்ணில் ஏறி கண்ணில் பாயும் புலரே என் மீதி வாழ்க்கையின் தலைப்பு நீ  கொஞ்சலி கொஞ்சலி ராவெல்லாம் நீ என் ஜோலி கொஞ்சலி கொஞ்சலி மஞ்சத்தில் நான் உன் ஜோலி கொஞ்சலி கொஞ்சலி ராவெல்லாம் நீ என் ஜோலி  "}