{"திரைப்படம்": "Mythili Ennai Kaathali", "பாடலாசிரியர்": "", "இசையமைப்பாளர்": "T. Rajendar", "பாடல்": "எங்கும் மைதிலி எதிலும் மைதிலி", "வருடம்": "1986", "பாடியவர்கள்": "S. P. Balasubramaniam", "பாடல்வரிகள்": "எங்கும் மைதிலி எதிலும் மைதிலி எல்லாம் மைதிலி என்னுயிர் மைதிலி அம்மம்மா மைதிலி அன்பானேன் மைதிலி  எங்கும் மைதிலி எதிலும் மைதிலி எல்லாம் மைதிலி என்னுயிர் மைதிலி அம்மம்மா மைதிலி அ.. அன்பானேன் மைதிலி  பார்க்கத் துடிப்பேன் மைதிலி பேசத் துடிப்பேன் மைதிலி பார்க்கத் துடிப்பேன் மைதிலி பேசத் துடிப்பேன் மைதிலி  நினைத்துப் பார்ப்பேன் மைதிலி நெஞ்சில் சுமப்பேன் மைதிலி நினைத்துப் பார்ப்பேன் மைதிலி நெஞ்சில் சுமப்பேன் மைதிலி  மைதிலி மைதிலி மைதிலி மைதிலி மைதிலி மைதிலி  எங்கும் மைதிலி எதிலும் மைதிலி எல்லாம் மைதிலி என்னுயிர் மைதிலி அம்மம்மா மைதிலி அன்பானேன் மைதிலி  மைதிலி மைதிலி ஹோஹோஹோ மைதிலி மைதிலி ஹோஹோ மைதிலி மைதிலி"}