{"திரைப்படம்": "Kaadhal Oviyam", "பாடலாசிரியர்": "Panchu Arunachalam", "இசையமைப்பாளர்": "Ilaiyaraaja", "பாடல்": "குயிலே குயிலே", "வருடம்": "1982", "பாடியவர்கள்": "S. Janaki, S. P. Balasubramaniam", "பாடல்வரிகள்": "குயிலே குயிலே உந்தன் கீதங்கள் கேட்காதோ  குயிலே குயிலே உந்தன் கீதங்கள் கேட்காதோ குயிலே குயிலே உந்தன் கீதங்கள் கேட்காதோ  உயிரே உறவே அந்த காலங்கள் வாராதோ  குயிலே குயிலே உந்தன் கீதங்கள் கேட்காதோ  ஆ ஆ ஆ வானத்து நிலவை தண்ணீரிலே சிறைவைத்த கதை தான் உன் கடையே வானத்து நிலவை தண்ணீரிலே சிறைவைத்த கதை தான் உன் கடையே  விழிகள் இருந்தும் உன்னை காணாமல் சுகம் ஏது அழகே மலரே வருவாய்யா  ஆ ஆ ஆ  குயிலே குயிலே உந்தன் கீதங்கள் கேட்காதோ  சீர்கொண்ட கவிதை கலைந்ததம்மா நான் கண்ட கனவும் மறைந்ததம்மா  சீர்கொண்ட கவிதை கலைந்ததம்மா நான் கண்ட கனவும் மறைந்ததம்மா சலங்கை இசையை நான் கேட்கின்ற காலம் ஏது  நினைவில் உனை நான் மறப்பேனா  ஆ ஆ ஆ  குயிலே குயிலே உந்தன் கீதங்கள் கேட்காதோ  உயிரே உறவே அந்த காலங்கள் வாராதோ  குயிலே குயிலே உந்தன் கீதங்கள் கேட்காதோ"}