{"திரைப்படம்": "Paarthal Pasi Theerum", "பாடலாசிரியர்": "Kannadasan", "இசையமைப்பாளர்": "Viswanathan Ramamoorthy", "பாடல்": "யாருக்கு மாப்பிள்ளை", "வருடம்": "1962", "பாடியவர்கள்": "P. Susheela", "பாடல்வரிகள்": "யாருக்கு மாப்பிள்ளை யாரோ அவர் எங்கே பிறந்திருக்கின்றாரோ ஓ ..ஓ ..ஓ. எந்தப் பார்வை பட்டு சொந்த உள்ளம் கெட்டு எங்கே மயங்கி நின்றாரோ (யாருக்கு…)  கட்டவிழ்ந்து கண் மயங்குவாரோ அதில் கைகலந்து காதல் புரிவாரோ தொட்டுத் தொட்டுப் பேசி மகிழ்வாரோ இல்லை தூர நின்று ஜாடை புரிவாரோ (யாருக்கு…)  ஊர் அறிய மாலையிடுவாரோ இல்லை ஓடிவிட எண்ணமிடுவாரோ சீர் வரிசை தேடி வருவாரோ இல்லை சின்ன இடை எண்ணி வருவாரோ (யாருக்கு…)"}